music_geometry_eval/__init__.py
music_geometry_eval/music_geometry_eval.py
music_geometry_eval-2.0.dist-info/LICENSE
music_geometry_eval-2.0.dist-info/METADATA
music_geometry_eval-2.0.dist-info/WHEEL
music_geometry_eval-2.0.dist-info/top_level.txt
music_geometry_eval-2.0.dist-info/RECORD
