Metadata-Version: 2.1
Name: music-geometry-eval
Version: 2.0
Summary: A python library to automatically evaluate music tonality based on geometry
Home-page: https://github.com/sebasgverde/music-geometry-eval
Author: Sebastian Garcia Valencia
Author-email: sebasgverde@gmail.com
License: MIT
Platform: UNKNOWN
Requires-Python: >=2.7
